{
  "slug": "isolador-galvanico-vs-transformador-isolamento",
  "kind": "comparison_cards",
  "title": "Isolador galvanico vs transformador de isolamento",
  "summary": "Comparativo entre protecao contra correntes galvanicas e isolamento eletrico completo da entrada AC.",
  "didactic_goal": "Diferenciar mitigacao galvanica de barreira eletrica completa na interface com o cais.",
  "format": "quadro-comparativo",
  "priority": "alta",
  "hero_label": "AMBOS REDUZEM PROBLEMAS DO CAIS, MAS NAO FAZEM A MESMA COISA",
  "notes": [
    "Isolador galvanico atua principalmente em baixas tensoes galvanicas no condutor de protecao.",
    "Transformador de isolamento cria separacao eletrica entre primario e secundario.",
    "Custo, peso, instalacao e manutencao sao bem diferentes.",
    "Escolha depende do risco, porte e arquitetura do barco."
  ],
  "caution": "A aplicacao correta depende de norma, fabricante, aterramento, protecao diferencial e topologia de entrada.",
  "target_notes": [
    "40_Distribuicao_Protecao_e_Aterramento/Isolador Galvanico - Transformador de Isolamento.md",
    "30_Energia_e_Conversao/CAIS (Pier) (AC).md"
  ],
  "columns": 2,
  "cards": [
    {"title": "Isolador galvanico", "detail": "Bloqueia pequenas tensoes galvanicas no caminho de protecao, mantendo funcao de seguranca para falhas maiores conforme especificacao.", "color": "#1D6FD8", "items": ["menor peso", "menor custo", "protege contra corrosao galvanica"]},
    {"title": "Transformador de isolamento", "detail": "Separa eletricamente marina e barco, criando secundario proprio para o sistema de bordo.", "color": "#7C5CC4", "items": ["barreira completa", "maior peso", "topologia propria"]}
  ]
}
